sqlnbfmt/__init__.py
sqlnbfmt/formatter.py
sqlnbfmt-0.1.9.dist-info/LICENSE
sqlnbfmt-0.1.9.dist-info/METADATA
sqlnbfmt-0.1.9.dist-info/WHEEL
sqlnbfmt-0.1.9.dist-info/entry_points.txt
sqlnbfmt-0.1.9.dist-info/top_level.txt
sqlnbfmt-0.1.9.dist-info/RECORD
