Metadata-Version: 2.2
Name: sqlnbfmt
Version: 0.1.9
Summary: A tool to format SQL code in Jupyter notebooks.
Author-email: Qing <qingye779@gmail.com>
License: MIT
Classifier: Programming Language :: Python :: 3
Classifier: Programming Language :: Python :: 3.12
Requires-Python: >=3.12
License-File: LICENSE
Requires-Dist: astor>=0.8.1
Requires-Dist: black>=24.10.0
Requires-Dist: nbformat>=5.10.4
Requires-Dist: pyyaml>=6.0.2
Requires-Dist: sqlglot>=25.27.0
